License
doc/Makefile
doc/conf.py
doc/index.rst
doc/make.bat
src/classes/__init__.py
src/classes/cli.py
src/classes/gitinterface.py
src/classes/gitmodules.py
src/classes/lstripreader.py
src/classes/utils.py
src/git-fleximod
tests/__init__.py
tests/test_import.py
tests/test_import.py~
git_fleximod-0.5.0.dist-info/METADATA
git_fleximod-0.5.0.dist-info/WHEEL
git_fleximod-0.5.0.dist-info/RECORD
