Metadata-Version: 2.1
Name: git-fleximod
Version: 0.5.0
Summary: Extended support for git-submodule and git-sparse-checkout
Home-page: https://github.com/jedwards4b/git-fleximod
License: MIT
Keywords: git,submodule,sparse-checkout
Author: Jim Edwards
Author-email: jedwards@ucar.edu
Maintainer: Jim Edwards
Maintainer-email: jedwards@ucar.edu
Requires-Python: >=3.8,<4.0
Classifier: License :: OSI Approved :: MIT License
Classifier: Programming Language :: Python :: 3
Classifier: Programming Language :: Python :: 3.8
Classifier: Programming Language :: Python :: 3.9
Classifier: Programming Language :: Python :: 3.10
Classifier: Programming Language :: Python :: 3.11
Classifier: Programming Language :: Python :: 3.12
Requires-Dist: GitPython (>=3.1.0,<4.0.0)
